MANIFEST.in
README.rst
setup.py
aliyun_python_sdk_cr_test.egg-info/PKG-INFO
aliyun_python_sdk_cr_test.egg-info/SOURCES.txt
aliyun_python_sdk_cr_test.egg-info/dependency_links.txt
aliyun_python_sdk_cr_test.egg-info/requires.txt
aliyun_python_sdk_cr_test.egg-info/top_level.txt
aliyunsdkcr/__init__.py
aliyunsdkcr/request/__init__.py
aliyunsdkcr/request/v20150506/DoCheckResourceRequest.py
aliyunsdkcr/request/v20150506/DoLogicalDeleteResourceRequest.py
aliyunsdkcr/request/v20150506/DoPhysicalDeleteResourceRequest.py
aliyunsdkcr/request/v20150506/__init__.py
aliyunsdkcr/request/v20160607/CancelRepoBuildRequest.py
aliyunsdkcr/request/v20160607/CreateCollectionRequest.py
aliyunsdkcr/request/v20160607/CreateNamespaceAuthorizationRequest.py
aliyunsdkcr/request/v20160607/CreateNamespaceRequest.py
aliyunsdkcr/request/v20160607/CreateRepoAuthorizationRequest.py
aliyunsdkcr/request/v20160607/CreateRepoBuildRuleRequest.py
aliyunsdkcr/request/v20160607/CreateRepoRequest.py
aliyunsdkcr/request/v20160607/CreateRepoSyncTaskRequest.py
aliyunsdkcr/request/v20160607/CreateRepoWebhookRequest.py
aliyunsdkcr/request/v20160607/CreateUserInfoRequest.py
aliyunsdkcr/request/v20160607/CreateUserSourceAccountRequest.py
aliyunsdkcr/request/v20160607/DeleteCollectionRequest.py
aliyunsdkcr/request/v20160607/DeleteImageRequest.py
aliyunsdkcr/request/v20160607/DeleteNamespaceAuthorizationRequest.py
aliyunsdkcr/request/v20160607/DeleteNamespaceRequest.py
aliyunsdkcr/request/v20160607/DeleteRepoAuthorizationRequest.py
aliyunsdkcr/request/v20160607/DeleteRepoBuildRuleRequest.py
aliyunsdkcr/request/v20160607/DeleteRepoRequest.py
aliyunsdkcr/request/v20160607/DeleteRepoWebhookRequest.py
aliyunsdkcr/request/v20160607/DeleteUserSourceAccountRequest.py
aliyunsdkcr/request/v20160607/GetAuthorizationTokenRequest.py
aliyunsdkcr/request/v20160607/GetCollectionRequest.py
aliyunsdkcr/request/v20160607/GetImageLayerRequest.py
aliyunsdkcr/request/v20160607/GetImageManifestRequest.py
aliyunsdkcr/request/v20160607/GetImageScanRequest.py
aliyunsdkcr/request/v20160607/GetMirrorListRequest.py
aliyunsdkcr/request/v20160607/GetNamespaceAuthorizationListRequest.py
aliyunsdkcr/request/v20160607/GetNamespaceListRequest.py
